belat/__about__.py
belat/__init__.py
belat/cli.py
belat/exceptions.py
belat/fileprocessor.py
belat/schemes/__init__.py
belat/schemes/classic.py
belat/schemes/gost1687671tb1.py
belat/schemes/gost1687671tb2.py
belat/schemes/gost7792000sysa.py
belat/schemes/gost7792000sysb.py
belat/schemes/official.py
belat-1.1.dist-info/METADATA
belat-1.1.dist-info/WHEEL
belat-1.1.dist-info/entry_points.txt
belat-1.1.dist-info/licenses/LICENSE
belat-1.1.dist-info/RECORD
