Metadata-Version: 2.3
Name: belat
Version: 1.1
Summary: Converter of belarussian latin font to cyrillic (and back)
Project-URL: Documentation, https://github.com/Alexander Rusakevich/belat#readme
Project-URL: Issues, https://github.com/Alexander Rusakevich/belat/issues
Project-URL: Source, https://github.com/Alexander Rusakevich/belat
Author-email: Alexander Rusakevich <mr.alexander.rusakevich@gmail.com>
License-Expression: MIT
License-File: LICENSE
Classifier: Development Status :: 4 - Beta
Classifier: Programming Language :: Python
Classifier: Programming Language :: Python :: 3.8
Classifier: Programming Language :: Python :: 3.9
Classifier: Programming Language :: Python :: 3.10
Classifier: Programming Language :: Python :: 3.11
Classifier: Programming Language :: Python :: 3.12
Classifier: Programming Language :: Python :: Implementation :: CPython
Classifier: Programming Language :: Python :: Implementation :: PyPy
Requires-Python: >=3.8
Requires-Dist: beautifulsoup4
Requires-Dist: lxml
